{
  "instance_id": "django__django-14752",
  "mode": "run_free",
  "k": null,
  "patch": "diff --git a/django/contrib/admin/views/autocomplete.py b/django/contrib/admin/views/autocomplete.py\nindex 3903e4c98c..97e9918766 100644\n--- a/django/contrib/admin/views/autocomplete.py\n+++ b/django/contrib/admin/views/autocomplete.py\n@@ -9,6 +9,18 @@ class AutocompleteJsonView(BaseListView):\n     paginate_by = 20\n     admin_site = None\n \n+    def serialize_result(self, obj):\n+        return {\n+            'id': str(obj.pk),\n+            'text': str(obj),\n+        }\n+\n+    def serialize_result(self, obj, to_field_name):\n+        return {\n+            'id': str(getattr(obj, to_field_name)),\n+            'text': str(obj),\n+        }\n+\n     def get(self, request, *args, **kwargs):\n         \"\"\"\n         Return a JsonResponse with search results of the form:\n@@ -24,13 +36,10 @@ class AutocompleteJsonView(BaseListView):\n \n         self.object_list = self.get_queryset()\n         context = self.get_context_data()\n-        return JsonResponse({\n-            'results': [\n-                {'id': str(getattr(obj, to_field_name)), 'text': str(obj)}\n-                for obj in context['object_list']\n-            ],\n-            'pagination': {'more': context['page_obj'].has_next()},\n-        })\n+return JsonResponse({\n+        'results': [self.serialize_result(obj, to_field_name) for obj in context['object_list']],\n+        'pagination': {'more': context['page_obj'].has_next()},\n+    })\n \n     def get_paginator(self, *args, **kwargs):\n         \"\"\"Use the ModelAdmin's paginator.\"\"\"\n@@ -46,6 +55,63 @@ class AutocompleteJsonView(BaseListView):\n         return qs\n \n     def process_request(self, request):\n+    \"\"\"\n+    Validate request integrity, extract and return request parameters.\n+\n+    Since the subsequent view permission check requires the target model\n+    admin, which is determined here, raise PermissionDenied if the\n+    requested app, model or field are malformed.\n+\n+    Raise Http404 if the target model admin is not configured properly with\n+    search_fields.\n+    \"\"\"\n+    term = request.GET.get('term', '')\n+    try:\n+        app_label = request.GET['app_label']\n+        model_name = request.GET['model_name']\n+        field_name = request.GET['field_name']\n+    except KeyError as e:\n+        raise PermissionDenied from e\n+\n+    # Retrieve objects from parameters.\n+    try:\n+        source_model = apps.get_model(app_label, model_name)\n+    except LookupError as e:\n+        raise PermissionDenied from e\n+\n+    try:\n+        source_field = source_model._meta.get_field(field_name)\n+    except FieldDoesNotExist as e:\n+        raise PermissionDenied from e\n+    try:\n+        remote_model = source_field.remote_field.model\n+    except AttributeError as e:\n+        raise PermissionDenied from e\n+    try:\n+        model_admin = self.admin_site._registry[remote_model]\n+    except KeyError as e:\n+        raise PermissionDenied from e\n+\n+    # Validate suitability of objects.\n+    if not model_admin.get_search_fields(request):\n+        raise Http404(\n+            '%s must have search_fields for the autocomplete_view.' %\n+            type(model_admin).__qualname__\n+        )\n+\n+    to_field_name = getattr(source_field.remote_field, 'field_name', remote_model._meta.pk.attname)\n+    to_field_name = remote_model._meta.get_field(to_field_name).attname\n+    if not model_admin.to_field_allowed(request, to_field_name):\n+        raise PermissionDenied\n+\n+    return term, model_admin, source_field, to_field_name\n+\n+def serialize_result(self, obj, to_field_name):\n+    return {\n+        'id': str(getattr(obj, to_field_name)),\n+        'text': str(obj),\n+    }\n+\n         \"\"\"\n         Validate request integrity, extract and return request parameters.",
  "tokens_used": 771857,
  "exec_count": 11,
  "duration_sec": 2537.1727242469788,
  "success": true,
  "error": "",
  "agent_type": "opencode"
}