{
  "instance_id": "django__django-14730",
  "mode": "run_cost",
  "k": null,
  "patch": "---\n## Goal\n\nPrevent developers from defining a `related_name` on `ManyToManyField` when the `symmetrical` argument is passed or in self-referential `ManyToMany` relationships.\n\n## Instructions\n\n- Read and analyze the source code to understand the bug.\n- Run tests/experiments as needed to verify understanding and test the fix.\n- Generate a fix using the Edit tool to modify source files.\n- Ensure the fix raises an error when a `related_name` is defined on a `ManyToManyField` with `symmetrical=True` or in a self-referential relationship.\n\n## Discoveries\n\n- The `ManyToManyField` class is located in `django/db/models/fields/related.py`.\n- The `symmetrical` attribute is handled within the `ManyToManyField` class.\n- The current implementation does not enforce an error when a `related_name` is defined on a `ManyToManyField` that is `symmetrical`.\n\n## Accomplished\n\n- Identified the relevant file (`django/db/models/fields/related.py`) and the relevant class (`ManyToManyField`).\n- Analyzed the implementation of the `ManyToManyField` class to understand how the `symmetrical` attribute is processed.\n- No immediate fix has been applied; the code analysis is still ongoing to determine the best place to insert the error-raising logic.\n\n## Relevant files / directories\n\n- `/testbed/django/db/models/fields/related.py`\n- `/testbed/django/db/models/fields/__init__.py`\n- `/testbed/django/db/models/fields/related_descriptors.py`\n- `/testbed/django/db/models/options.py`\n- `/testbed/django/core/checks/model_checks.py`\n- `/testbed/django/core/exceptions.py`\n- `/testbed/django/utils/translation.py`\n- `/testbed/django/conf/global_settings.py`\n- `/testbed/django/contrib/contenttypes/fields.py`\n- `/testbed/django/contrib/contenttypes/models.py`\n\nThese files provide context for the `ManyToManyField` implementation and related functionalities.\n---\nContinue if you have next steps, or stop and ask for clarification if you are unsure how to proceed.\nTo proceed, I will add a check in the `ManyToManyField` class to raise an error when a `related_name` is defined on a `ManyToManyField` that is either `symmetrical=True` or in a self-referential relationship. I will also add tests to ensure the fix works correctly.\n\n### Steps:\n1. **Read the `ManyToManyField` class** to understand the current implementation and determine the best place to add the check.\n2. **Edit the `ManyToManyField` class** to include the error-raising logic.\n3. **Create or modify tests** to verify the fix.\n\nLet's start by reading the `ManyToManyField` class.\nI will now identify the appropriate place to add the error-raising logic within the `ManyToManyField` class to prevent defining a `related_name` when `symmetrical=True` or in self-referential relationships.\n\n### Steps:\n1. **Identify the place** to add the check.\n2. **Edit the `ManyToManyField` class** to include the error-raising logic.\n3. **Create or modify tests** to verify the fix.\n\n### Analysis:\n- The `ManyToManyField` class is defined around lines 1155-1310.\n- The `__init__` method initializes the field with various parameters, including `symmetrical`, `through`, and `related_name`.\n- The `_check_relationship_model` method seems like an appropriate place to add the new validation logic since it checks the relationship model and other related configurations.\n\nLet's add the error-raising logic to the `_check_relationship_model` method.",
  "tokens_used": 252334,
  "exec_count": 0,
  "duration_sec": 545.8266229629517,
  "success": true,
  "error": "",
  "agent_type": "opencode"
}