{
  "instance_id": "django__django-12908",
  "mode": "run_less",
  "k": 3,
  "patch": "diff --git a/django/db/models/query.py b/django/db/models/query.py\nindex e0eeccefa6..6d18929423 100644\n--- a/django/db/models/query.py\n+++ b/django/db/models/query.py\n@@ -1135,6 +1135,9 @@ class QuerySet:\n         return obj\n \n     def distinct(self, *field_names):\n+        import logging\n+        logging.basicConfig(level=logging.DEBUG)\n+        logging.debug(self.query.get_compiler(using='default').as_sql())\n         \"\"\"\n         Return a new QuerySet instance that will select only distinct results.\n         \"\"\"",
  "tokens_used": 78550,
  "exec_count": 6,
  "duration_sec": 348.76991963386536,
  "success": true,
  "error": "",
  "agent_type": "opencode"
}